sc/__init__.py
sc/_compat.py
sc/conversions.py
sc/main.py
ScreenCalc-0.1.0.dist-info/DESCRIPTION.rst
ScreenCalc-0.1.0.dist-info/entry_points.txt
ScreenCalc-0.1.0.dist-info/METADATA
ScreenCalc-0.1.0.dist-info/metadata.json
ScreenCalc-0.1.0.dist-info/RECORD
ScreenCalc-0.1.0.dist-info/top_level.txt
ScreenCalc-0.1.0.dist-info/WHEEL
tests/__init__.py
tests/test_cli.py
tests/test_conversions.py
tests/test_parser.py
