Metadata-Version: 2.0
Name: ScreenCalc
Version: 0.1.0
Summary: ScreenCalc is a Python 3 package template.
Home-page: https://github.com/joshfriend/screencalc
Author: Josh Friend
Author-email: josh@fueledbycaffeine.com
License: MIT
Platform: UNKNOWN
Classifier: Development Status :: 1 - Planning
Classifier: Natural Language :: English
Classifier: Operating System :: OS Independent
Classifier: Programming Language :: Python :: 3.3
Requires-Dist: tabulate
Requires-Dist: click
